[
  {
    "handle": "Six Things (ITL Focus)",
    "platform_primary": "newsletter",
    "influencer_type": "newsletter",
    "subscriber_count": 24000,
    "topic_focus": "Risk & Innovation - P&C Insurance",
    "frequency": "weekly",
    "sponsorship_pricing": "Custom",
    "icp_target": "insurance_ops",
    "icp_fit_label": "Very High",
    "priority_rank": 1,
    "contact_info": "Paul Carroll - contact via ITL partner team",
    "profile_url": "https://insurancethoughtleadership.com",
    "lead_tier": "tier_1",
    "lead_score": 9,
    "topics": ["insurance", "risk", "innovation"]
  },
  {
    "handle": "CFO Secrets",
    "platform_primary": "newsletter",
    "influencer_type": "newsletter",
    "subscriber_count": 50000,
    "topic_focus": "CFO Leadership & Financial Operations",
    "frequency": "weekly",
    "sponsorship_pricing": "Flat Rate",
    "icp_target": "finance_ops",
    "icp_fit_label": "Very High",
    "priority_rank": 2,
    "contact_info": "Sponsor form at cfosecrets.io",
    "profile_url": "https://cfosecrets.io",
    "lead_tier": "tier_1",
    "lead_score": 9,
    "topics": ["finance", "cfo", "operations"]
  },
  {
    "handle": "Mostly Metrics",
    "platform_primary": "newsletter",
    "influencer_type": "newsletter",
    "subscriber_count": 64000,
    "topic_focus": "SaaS Finance & Metrics",
    "frequency": "weekly",
    "sponsorship_pricing": "Premium CPM",
    "icp_target": "finance_ops",
    "icp_fit_label": "Very High",
    "priority_rank": 3,
    "contact_info": "CJ Gustafson - sponsor form at mostlymetrics.com",
    "profile_url": "https://mostlymetrics.com",
    "lead_tier": "tier_1",
    "lead_score": 9,
    "topics": ["finance", "saas", "metrics"]
  },
  {
    "handle": "Nerd's Eye View",
    "platform_primary": "newsletter",
    "influencer_type": "newsletter",
    "subscriber_count": 15000,
    "topic_focus": "RIA & Wealth Management",
    "frequency": "weekly",
    "sponsorship_pricing": "Premium",
    "icp_target": "finance_ops",
    "icp_fit_label": "Very High",
    "priority_rank": 4,
    "contact_info": "Michael Kitces - sponsor form at kitces.com",
    "profile_url": "https://kitces.com",
    "lead_tier": "tier_1",
    "lead_score": 9,
    "topics": ["finance", "wealth", "ria"]
  },
  {
    "handle": "Healthcare Brew",
    "platform_primary": "newsletter",
    "influencer_type": "newsletter",
    "subscriber_count": 100000,
    "topic_focus": "Healthcare Administration & Ops",
    "frequency": "3x/Week",
    "sponsorship_pricing": "Premium",
    "icp_target": "healthcare_ops",
    "icp_fit_label": "Very High",
    "priority_rank": 5,
    "contact_info": "Morning Brew Partnerships team",
    "profile_url": "https://healthcarebrew.com",
    "lead_tier": "tier_1",
    "lead_score": 9,
    "topics": ["healthcare", "operations", "admin"]
  },
  {
    "handle": "Unsupervised Learning",
    "platform_primary": "newsletter",
    "influencer_type": "newsletter",
    "subscriber_count": 94000,
    "topic_focus": "Security & AI Operations",
    "frequency": "weekly",
    "sponsorship_pricing": "Premium",
    "icp_target": "ai_ops",
    "icp_fit_label": "Very High",
    "priority_rank": 6,
    "contact_info": "Daniel Miessler - sponsor form at danielmiessler.com",
    "profile_url": "https://danielmiessler.com",
    "lead_tier": "tier_1",
    "lead_score": 9,
    "topics": ["security", "ai", "operations"]
  },
  {
    "handle": "LawNext / LawSites",
    "platform_primary": "newsletter",
    "influencer_type": "newsletter",
    "subscriber_count": null,
    "topic_focus": "Legal Tech & Operations",
    "frequency": "weekly",
    "sponsorship_pricing": "~$1,000/mo",
    "icp_target": "legal_ops",
    "icp_fit_label": "Very High",
    "priority_rank": 7,
    "contact_info": "Bob Ambrogi - ben@lawnextmedia.com",
    "profile_url": "https://lawnext.com",
    "lead_tier": "tier_1",
    "lead_score": 9,
    "topics": ["legal", "tech", "operations"]
  },
  {
    "handle": "MKT1",
    "platform_primary": "newsletter",
    "influencer_type": "newsletter",
    "subscriber_count": 50000,
    "topic_focus": "B2B Marketing Operations",
    "frequency": "monthly",
    "sponsorship_pricing": "Flat Rate",
    "icp_target": "marketing_ops",
    "icp_fit_label": "High",
    "priority_rank": 8,
    "contact_info": "Emily Kramer - sponsor form at mkt1.substack.com",
    "profile_url": "https://mkt1.substack.com",
    "lead_tier": "tier_1",
    "lead_score": 8,
    "topics": ["marketing", "b2b", "operations"]
  },
  {
    "handle": "Digital Insurance",
    "platform_primary": "newsletter",
    "influencer_type": "newsletter",
    "subscriber_count": 127000,
    "topic_focus": "Insurtech & Digital Operations",
    "frequency": "daily",
    "sponsorship_pricing": "Media Kit",
    "icp_target": "insurance_ops",
    "icp_fit_label": "High",
    "priority_rank": 9,
    "contact_info": "Arizent - media kit request at dig-in.com",
    "profile_url": "https://dig-in.com",
    "lead_tier": "tier_1",
    "lead_score": 8,
    "topics": ["insurance", "insurtech", "digital"]
  },
  {
    "handle": "Carrier Management",
    "platform_primary": "newsletter",
    "influencer_type": "newsletter",
    "subscriber_count": 49000,
    "topic_focus": "C-Suite P&C Insurance",
    "frequency": "weekly",
    "sponsorship_pricing": "Media Kit",
    "icp_target": "insurance_ops",
    "icp_fit_label": "High",
    "priority_rank": 10,
    "contact_info": "Wells Media Group - media kit request",
    "profile_url": "https://carriermanagement.com",
    "lead_tier": "tier_1",
    "lead_score": 8,
    "topics": ["insurance", "c-suite"]
  },
  {
    "handle": "OnlyCFO",
    "platform_primary": "newsletter",
    "influencer_type": "newsletter",
    "subscriber_count": 15000,
    "topic_focus": "High-Growth Finance",
    "frequency": "bi-weekly",
    "sponsorship_pricing": "Premium CPM",
    "icp_target": "finance_ops",
    "icp_fit_label": "High",
    "priority_rank": 11,
    "contact_info": "Sponsor form at onlycfo.substack.com",
    "profile_url": "https://onlycfo.substack.com",
    "lead_tier": "tier_2",
    "lead_score": 8,
    "topics": ["finance", "growth"]
  },
  {
    "handle": "Stacked Marketer",
    "platform_primary": "newsletter",
    "influencer_type": "newsletter",
    "subscriber_count": 90000,
    "topic_focus": "Digital Marketing Operations",
    "frequency": "daily",
    "sponsorship_pricing": "Flat Rate",
    "icp_target": "marketing_ops",
    "icp_fit_label": "High",
    "priority_rank": 12,
    "contact_info": "Sponsor form at stackedmarketer.com",
    "profile_url": "https://stackedmarketer.com",
    "lead_tier": "tier_2",
    "lead_score": 8,
    "topics": ["marketing", "digital"]
  },
  {
    "handle": "Demand Curve",
    "platform_primary": "newsletter",
    "influencer_type": "newsletter",
    "subscriber_count": 101000,
    "topic_focus": "Growth Strategy",
    "frequency": "weekly",
    "sponsorship_pricing": "Premium",
    "icp_target": "marketing_ops",
    "icp_fit_label": "High",
    "priority_rank": 13,
    "contact_info": "Julian Shapiro - sponsor form at demandcurve.com",
    "profile_url": "https://demandcurve.com",
    "lead_tier": "tier_2",
    "lead_score": 8,
    "topics": ["growth", "strategy"]
  },
  {
    "handle": "HR Jolt",
    "platform_primary": "newsletter",
    "influencer_type": "newsletter",
    "subscriber_count": 18000,
    "topic_focus": "HR Strategy",
    "frequency": "weekly",
    "sponsorship_pricing": "Custom CPM",
    "icp_target": "hr_ops",
    "icp_fit_label": "High",
    "priority_rank": 14,
    "contact_info": "Beehiiv Network",
    "profile_url": "https://beehiiv.com",
    "lead_tier": "tier_2",
    "lead_score": 7,
    "topics": ["hr", "strategy"]
  },
  {
    "handle": "People Ops Weekly",
    "platform_primary": "newsletter",
    "influencer_type": "newsletter",
    "subscriber_count": 13000,
    "topic_focus": "People Operations Leaders",
    "frequency": "bi-weekly",
    "sponsorship_pricing": "Custom",
    "icp_target": "hr_ops",
    "icp_fit_label": "High",
    "priority_rank": 15,
    "contact_info": "ChartHop - sponsor form at charthop.com",
    "profile_url": "https://charthop.com",
    "lead_tier": "tier_2",
    "lead_score": 7,
    "topics": ["hr", "people_ops"]
  },
  {
    "handle": "Workology",
    "platform_primary": "newsletter",
    "influencer_type": "newsletter",
    "subscriber_count": 80000,
    "topic_focus": "HR Professionals & Operations",
    "frequency": "weekly",
    "sponsorship_pricing": "Media Kit",
    "icp_target": "hr_ops",
    "icp_fit_label": "High",
    "priority_rank": 16,
    "contact_info": "J. Miller-Merrell - ad dept at workology.com",
    "profile_url": "https://workology.com",
    "lead_tier": "tier_2",
    "lead_score": 7,
    "topics": ["hr", "operations"]
  },
  {
    "handle": "The Brainyacts",
    "platform_primary": "newsletter",
    "influencer_type": "newsletter",
    "subscriber_count": null,
    "topic_focus": "AI Tips for Lawyers",
    "frequency": "weekly",
    "sponsorship_pricing": "Custom",
    "icp_target": "legal_ops",
    "icp_fit_label": "Very High",
    "priority_rank": 17,
    "contact_info": "Josh Kubicki - Beehiiv Network",
    "profile_url": "https://beehiiv.com",
    "lead_tier": "tier_1",
    "lead_score": 9,
    "topics": ["legal", "ai"]
  },
  {
    "handle": "Insurance Journal Daily",
    "platform_primary": "newsletter",
    "influencer_type": "newsletter",
    "subscriber_count": 100000,
    "topic_focus": "P&C Insurance Operations",
    "frequency": "daily",
    "sponsorship_pricing": "Media Kit",
    "icp_target": "insurance_ops",
    "icp_fit_label": "High",
    "priority_rank": 18,
    "contact_info": "Wells Media Group - ads dept at insurancejournal.com",
    "profile_url": "https://insurancejournal.com",
    "lead_tier": "tier_2",
    "lead_score": 7,
    "topics": ["insurance", "operations"]
  },
  {
    "handle": "Propmodo",
    "platform_primary": "newsletter",
    "influencer_type": "newsletter",
    "subscriber_count": 70000,
    "topic_focus": "CRE Tech & Operations",
    "frequency": "weekly",
    "sponsorship_pricing": "Media Kit",
    "icp_target": "real_estate_ops",
    "icp_fit_label": "High",
    "priority_rank": 19,
    "contact_info": "Sponsor form at propmodo.com",
    "profile_url": "https://propmodo.com",
    "lead_tier": "tier_2",
    "lead_score": 7,
    "topics": ["real_estate", "tech"]
  },
  {
    "handle": "Real Estate Mgmt News",
    "platform_primary": "newsletter",
    "influencer_type": "newsletter",
    "subscriber_count": 43800,
    "topic_focus": "Property Management Operations",
    "frequency": "weekly",
    "sponsorship_pricing": "~$1,650/mo",
    "icp_target": "real_estate_ops",
    "icp_fit_label": "High",
    "priority_rank": 20,
    "contact_info": "IREM - yaffey@irem.org",
    "profile_url": "https://irem.org",
    "lead_tier": "tier_2",
    "lead_score": 7,
    "topics": ["real_estate", "property_mgmt"]
  },
  {
    "handle": "CFO Brew",
    "platform_primary": "newsletter",
    "influencer_type": "newsletter",
    "subscriber_count": 35000,
    "topic_focus": "Corporate Finance",
    "frequency": "3x/Week",
    "sponsorship_pricing": "Premium",
    "icp_target": "finance_ops",
    "icp_fit_label": "Medium",
    "priority_rank": 21,
    "contact_info": "Morning Brew Partnerships",
    "profile_url": "https://cfobrew.com",
    "lead_tier": "tier_2",
    "lead_score": 6,
    "topics": ["finance", "corporate"]
  },
  {
    "handle": "Hearsay",
    "platform_primary": "newsletter",
    "influencer_type": "newsletter",
    "subscriber_count": 3600,
    "topic_focus": "Canadian Legal Operations",
    "frequency": "weekly",
    "sponsorship_pricing": "Flat Rate",
    "icp_target": "legal_ops",
    "icp_fit_label": "Medium",
    "priority_rank": 22,
    "contact_info": "Dylan Gibbs - Beehiiv Network",
    "profile_url": "https://beehiiv.com",
    "lead_tier": "tier_2",
    "lead_score": 6,
    "topics": ["legal", "canada"]
  },
  {
    "handle": "Manufacturing.net",
    "platform_primary": "newsletter",
    "influencer_type": "newsletter",
    "subscriber_count": 13000,
    "topic_focus": "OT & Automation Management",
    "frequency": "weekly",
    "sponsorship_pricing": "Media Kit",
    "icp_target": "manufacturing_ops",
    "icp_fit_label": "Medium",
    "priority_rank": 23,
    "contact_info": "Industrial Media - ad dept",
    "profile_url": "https://manufacturing.net",
    "lead_tier": "tier_3",
    "lead_score": 5,
    "topics": ["manufacturing", "automation"]
  },
  {
    "handle": "Construction Eq. Guide",
    "platform_primary": "newsletter",
    "influencer_type": "newsletter",
    "subscriber_count": 35000,
    "topic_focus": "Construction Operations",
    "frequency": "weekly",
    "sponsorship_pricing": "$460/banner",
    "icp_target": "construction_ops",
    "icp_fit_label": "Low",
    "priority_rank": 24,
    "contact_info": "CEG Media - mediakit.constructionequipmentguide.com",
    "profile_url": "https://constructionequipmentguide.com",
    "lead_tier": "tier_3",
    "lead_score": 4,
    "topics": ["construction", "equipment"]
  },
  {
    "handle": "AI Governance Library",
    "platform_primary": "newsletter",
    "influencer_type": "newsletter",
    "subscriber_count": null,
    "topic_focus": "AI Policy & Compliance",
    "frequency": "weekly",
    "sponsorship_pricing": "Custom",
    "icp_target": "ai_ops",
    "icp_fit_label": "Very High",
    "priority_rank": 25,
    "contact_info": "Sponsor form at aigl.blog",
    "profile_url": "https://aigl.blog",
    "lead_tier": "tier_1",
    "lead_score": 9,
    "topics": ["ai", "governance", "compliance"]
  }
]
